[
    {
        "Compatibility": [
            "SVDS 7.62x54 Sniper rifle",
            "AKS-74 5.45x39 assault rifle",
            "AK-74 5.45x39 assault rifle",
            "Saiga 12ga ver. 10 12x76 assault rifle",
            "AK-103 7.62x39 assault rifle",
            "AKMS 7.62x39 assault rifle",
            "Saiga-9 9x19 Carbine",
            "AKMN 7.62x39 assault rifle",
            "AK-74N 5.45x39 assault rifle",
            "Vepr KM / VPO-136 7.62x39 carbine",
            "AK-74M 5.45x39 assault rifle",
            "AK-105 5.45x39 assault rifle",
            "Vepr AKM / VPO-209 366TKM carbine",
            "Submachinegun 19-01 Vityaz-SN 9x19",
            "AKM 7.62x39 assault rifle",
            "Kalashnikov AKS-74UB 5.45x39",
            "AKMSN 7.62x39 assault rifle",
            "AK-102 5.56x45 assault rifle",
            "Kalashnikov AKS-74U 5.45x39",
            "AK-101 5.56x45 assault rifle",
            "Kalashnikov AKS-74UN 5.45x39",
            "AK-104 7.62x39 assault rifle",
            "AKS-74N 5.45x39 assault rifle"
        ],
        "ergonomics": 12.0,
        "examineexperience": 2.0,
        "gridsize": "1x1",
        "itemLink": "https://escapefromtarkov.gamepedia.com/US_Palm_pistol_grip_for_AK",
        "itemName": "US Palm pistol grip for AK",
        "lootexperience": 5.0,
        "soldby": "Peacekeeper LL3",
        "type": "Pistol grip",
        "weight": 0.09
    },
    {
        "Compatibility": [
            "ADAR 2-15 .223 Carbine",
            "Colt M4A1 5.56x45 Assault Rifle",
            "HK 416A5 5.56x45 Assault Rifle",
            "SIG MPX 9x19 Submachine gun"
        ],
        "ergonomics": 7.0,
        "examineexperience": 2.0,
        "gridsize": "1x1",
        "itemLink": "https://escapefromtarkov.gamepedia.com/HK_Grip_V.2_pistol_grip_for_AR-15_based_systems",
        "itemName": "HK Grip V.2 pistol grip for AR-15 based systems",
        "lootexperience": 10.0,
        "soldby": "Peacekeeper LL3",
        "type": "Pistol grip",
        "weight": 0.08
    },
    {
        "Compatibility": [
            "SVDS 7.62x54 Sniper rifle"
        ],
        "ergonomics": 5.0,
        "examineexperience": 2.0,
        "gridsize": "1x1",
        "itemLink": "https://escapefromtarkov.gamepedia.com/Izhmash_SVDS_pistol_grip",
        "itemName": "Izhmash SVDS pistol grip",
        "lootexperience": 5.0,
        "type": "Pistol grip",
        "weight": 0.07
    },
    {
        "Compatibility": [
            "DT MDR 5.56x45 Assault Rifle"
        ],
        "ergonomics": 5.0,
        "examineexperience": 2.0,
        "gridsize": "1x1",
        "itemLink": "https://escapefromtarkov.gamepedia.com/Desert_Tech_pistol_grip_for_MDR",
        "itemName": "Desert Tech pistol grip for MDR",
        "lootexperience": 10.0,
        "soldby": "Mechanic LL3",
        "type": "Pistol grip",
        "weight": 0.08
    },
    {
        "Compatibility": [
            "TT pistol 7.62x25 TT",
            "TT pistol 7.62x25 TT Gold"
        ],
        "ergonomics": 13.0,
        "examineexperience": 2.0,
        "gridsize": "1x1",
        "itemLink": "https://escapefromtarkov.gamepedia.com/Razor_Arms_TT_rubber_grips",
        "itemName": "Razor Arms TT rubber grips",
        "lootexperience": 5.0,
        "recoil%": 0.0,
        "soldby": "Mechanic LL2",
        "type": "Pistol grip",
        "weight": 0.06
    },
    {
        "ergonomics": 8.0,
        "examineexperience": 2.0,
        "gridsize": "1x1",
        "itemLink": "https://escapefromtarkov.gamepedia.com/Hogue_like_TT_rubber_grips",
        "itemName": "Hogue like TT rubber grips",
        "lootexperience": 5.0,
        "recoil%": 0.0,
        "soldby": "Mechanic LL1",
        "type": "Pistol grip",
        "weight": 0.07
    },
    {
        "Compatibility": [
            "P226R 9x19 pistol"
        ],
        "ergonomics": 8.0,
        "examineexperience": 2.0,
        "gridsize": "1x1",
        "itemLink": "https://escapefromtarkov.gamepedia.com/Wooden_Sig_Sauer_Elite_pistol_grip_for_P226",
        "itemName": "Wooden Sig Sauer Elite pistol grip for P226",
        "lootexperience": 5.0,
        "recoil%": 0.0,
        "soldby": "Mechanic LL2",
        "type": "Pistol grip",
        "weight": 0.08
    },
    {
        "Compatibility": [
            "P226R 9x19 pistol"
        ],
        "ergonomics": 8.0,
        "examineexperience": 2.0,
        "gridsize": "1x1",
        "itemLink": "https://escapefromtarkov.gamepedia.com/Emperor_scorpion_Sig_Sauer_pistol_grip_for_P226",
        "itemName": "Emperor scorpion Sig Sauer pistol grip for P226",
        "lootexperience": 5.0,
        "recoil%": 0.0,
        "soldby": "Mechanic LL3",
        "type": "Pistol grip",
        "weight": 0.09
    },
    {
        "Compatibility": [
            "P226R 9x19 pistol"
        ],
        "ergonomics": 12.0,
        "examineexperience": 2.0,
        "gridsize": "1x1",
        "itemLink": "https://escapefromtarkov.gamepedia.com/Hogue_Chain_link_pistol_grip_for_P226",
        "itemName": "Hogue Chain link pistol grip for P226",
        "lootexperience": 5.0,
        "recoil%": 0.0,
        "soldby": "Mechanic LL2",
        "type": "Pistol grip",
        "weight": 0.09
    },
    {
        "Compatibility": [
            "P226R 9x19 pistol"
        ],
        "ergonomics": 7.0,
        "examineexperience": 2.0,
        "gridsize": "1x1",
        "itemLink": "https://escapefromtarkov.gamepedia.com/Axelson_Tacical_MK.25_pistol_grip_for_P226",
        "itemName": "Axelson Tacical MK.25 pistol grip for P226",
        "lootexperience": 5.0,
        "recoil%": 0.0,
        "soldby": "Mechanic LL3",
        "type": "Pistol grip",
        "weight": 0.09
    },
    {
        "Compatibility": [
            "TT pistol 7.62x25 TT"
        ],
        "ergonomics": 2.0,
        "examineexperience": 2.0,
        "gridsize": "1x1",
        "itemLink": "https://escapefromtarkov.gamepedia.com/PM-Laser_TT-206_side_grips_with_LAM",
        "itemName": "PM-Laser TT-206 side grips with LAM",
        "lootexperience": 5.0,
        "recoil%": 0.0,
        "soldby": "Mechanic LL2",
        "type": "Pistol grip",
        "weight": 0.09
    },
    {
        "Compatibility": [
            "Remington Model 870 12ga shotgun",
            "Stock adapter Tactica Tula 12003 for MP-133/153"
        ],
        "ergonomics": 9.0,
        "examineexperience": 2.0,
        "gridsize": "1x1",
        "itemLink": "https://escapefromtarkov.gamepedia.com/Fab_Defence_AGR-870_pistol_grip_for_Remington-870",
        "itemName": "Fab Defence AGR-870 pistol grip for Remington-870",
        "lootexperience": 5.0,
        "recoil%": 0.0,
        "soldby": "Skier LL4",
        "type": "Pistol grip",
        "weight": 0.13
    },
    {
        "Compatibility": [
            "SVDS 7.62x54 Sniper rifle",
            "AK-101 5.56x45 assault rifle",
            "AK-102 5.56x45 assault rifle",
            "AK-103 7.62x39 assault rifle",
            "AK-104 7.62x39 assault rifle",
            "AK-105 5.45x39 assault rifle",
            "AK-74 5.45x39 assault rifle",
            "AK-74M 5.45x39 assault rifle",
            "AK-74N 5.45x39 assault rifle",
            "AKM 7.62x39 assault rifle",
            "AKMN 7.62x39 assault rifle",
            "AKMS 7.62x39 assault rifle",
            "AKMSN 7.62x39 assault rifle",
            "AKS-74 5.45x39 assault rifle",
            "AKS-74N 5.45x39 assault rifle",
            "Kalashnikov AKS-74U 5.45x39",
            "Kalashnikov AKS-74UB 5.45x39",
            "Kalashnikov AKS-74UN 5.45x39",
            "RPK-16 5.45x39 light machine gun",
            "Saiga 12ga ver. 10 12x76 assault rifle",
            "Saiga-9 9x19 Carbine",
            "Submachinegun 19-01 Vityaz-SN 9x19",
            "Vepr AKM / VPO-209 366TKM carbine",
            "Vepr KM / VPO-136 7.62x39 carbine"
        ],
        "ergonomics": 7.0,
        "examineexperience": 5.0,
        "gridsize": "1x1",
        "itemLink": "https://escapefromtarkov.gamepedia.com/Izhmash_AK-12_regular_pistol_grip",
        "itemName": "Izhmash AK-12 regular pistol grip",
        "recoil%": 0.0,
        "soldby": "Prapor LL3",
        "type": "Pistol grip",
        "weight": 0.05
    },
    {
        "Compatibility": [
            "Regular Mosin rifle stock",
            "Sawn off Mosin rifle sniper stock",
            "Mosin carabine stock",
            "Mosin rifle sniper carabine stock",
            "Sawn off regular Mosin rifle stock",
            "Infantry Mosin rifle stock"
        ],
        "ergonomics": -1.0,
        "gridsize": "1x1",
        "itemLink": "https://escapefromtarkov.gamepedia.com/Tacfire_pistol_grip_for_Mosin_rifle",
        "itemName": "Tacfire pistol grip for Mosin rifle",
        "recoil%": -3.0,
        "soldby": "Mechanic LL2 after completing his task The Tarkov shooter - Part 4",
        "type": "Pistol grip",
        "weight": 0.16
    },
    {
        "Compatibility": [
            "ADAR 2-15 .223 Carbine",
            "Remington R11 RSASS 7.62x51",
            "Troy S.A.S.S. Chassis stock for M14",
            "HK 416A5 5.56x45 Assault Rifle",
            "Colt M4A1 5.56x45 Assault Rifle",
            "SIG MPX 9x19 Submachine gun"
        ],
        "ergonomics": 5.0,
        "gridsize": "1x1",
        "itemLink": "https://escapefromtarkov.gamepedia.com/HK_%22Battle_Grip%22_pistol_grip_for_AR-15_based_systems",
        "itemName": "HK \"Battle Grip\" pistol grip for AR-15 based systems",
        "recoil%": 0.0,
        "soldby": "Mechanic: LL4",
        "type": "Pistol grip",
        "weight": 0.08
    },
    {
        "Compatibility": [
            "ADAR 2-15 .223 Carbine",
            "LEO stock adapter for M870",
            "Colt M4A1 5.56x45 Assault Rifle",
            "HK 416A5 5.56x45 Assault Rifle",
            "Remington R11 RSASS 7.62x51",
            "SIG MPX 9x19 Submachine gun"
        ],
        "ergonomics": 6.0,
        "gridsize": "1x1",
        "itemLink": "https://escapefromtarkov.gamepedia.com/HK_Battle_Grip_with_Beavertail_pistol_grip_for_AR-15_based_systems",
        "itemName": "HK Battle Grip with Beavertail pistol grip for AR-15 based systems",
        "recoil%": 0.0,
        "soldby": "Mechanic: LL4",
        "type": "Pistol grip",
        "weight": 0.08
    },
    {
        "Compatibility": [
            "DS Arms SA-58 7.62x51"
        ],
        "ergonomics": 13.0,
        "gridsize": "1x1",
        "itemLink": "https://escapefromtarkov.gamepedia.com/Fab_AG_FAL_pistol_grip_for_SA-58",
        "itemName": "Fab AG FAL pistol grip for SA-58",
        "recoil%": 0.0,
        "soldby": "Mechanic LL4",
        "type": "Pistol grip",
        "weight": 0.088
    },
    {
        "Compatibility": [
            "DS Arms SA-58 7.62x51"
        ],
        "ergonomics": 5.0,
        "gridsize": "1x1",
        "itemLink": "https://escapefromtarkov.gamepedia.com/Regular_%22DS_Arms%22_pistol_grip_for_SA-58",
        "itemName": "Regular \"DS Arms\" pistol grip for SA-58",
        "recoil%": 0.0,
        "soldby": "Mechanic LL1",
        "type": "Pistol grip",
        "weight": 0.11
    },
    {
        "Compatibility": [
            "DS Arms SA-58 7.62x51"
        ],
        "ergonomics": 10.0,
        "gridsize": "1x1",
        "itemLink": "https://escapefromtarkov.gamepedia.com/TAPCO_SAW-Style_black_pistol_grip_for_SA-58",
        "itemName": "TAPCO SAW-Style black pistol grip for SA-58",
        "recoil%": 0.0,
        "soldby": "Mechanic LL2",
        "type": "Pistol grip",
        "weight": 0.13
    },
    {
        "Compatibility": [
            "P226R 9x19 pistol"
        ],
        "ergonomics": 10.0,
        "gridsize": "1x1",
        "itemLink": "https://escapefromtarkov.gamepedia.com/Rubber_with_finger_grooves_pistol_grip_for_P226",
        "itemName": "Rubber with finger grooves pistol grip for P226",
        "recoil%": 0.0,
        "soldby": "Mechanic LL2",
        "type": "Pistol grip",
        "weight": 0.07
    },
    {
        "Compatibility": [
            "AK-101 5.56x45 assault rifle",
            "AK-102 5.56x45 assault rifle",
            "AK-103 7.62x39 assault rifle",
            "AK-104 7.62x39 assault rifle",
            "AK-105 5.45x39 assault rifle",
            "AK-74 5.45x39 assault rifle",
            "AK-74M 5.45x39 assault rifle",
            "AK-74N 5.45x39 assault rifle",
            "AKM 7.62x39 assault rifle",
            "AKMN 7.62x39 assault rifle",
            "AKMS 7.62x39 assault rifle",
            "AKMSN 7.62x39 assault rifle",
            "AKS-74 5.45x39 assault rifle",
            "AKS-74N 5.45x39 assault rifle",
            "Kalashnikov AKS-74U 5.45x39",
            "Kalashnikov AKS-74UB 5.45x39",
            "Kalashnikov AKS-74UN 5.45x39",
            "RPK-16 5.45x39 light machine gun",
            "Saiga 12ga ver. 10 12x76 assault rifle",
            "Submachinegun 19-01 Vityaz-SN 9x19",
            "SVDS 7.62x54 Sniper rifle",
            "Vepr AKM / VPO-209 366TKM carbine",
            "Vepr KM / VPO-136 7.62x39 carbine"
        ],
        "ergonomics": 14.0,
        "gridsize": "1x1",
        "itemLink": "https://escapefromtarkov.gamepedia.com/Magpul_MOE_pistol_grip_for_AK",
        "itemName": "Magpul MOE pistol grip for AK",
        "recoil%": 0.0,
        "soldby": "Mechanic LL3",
        "type": "Pistol grip",
        "weight": 0.08
    },
    {
        "Compatibility": [
            "M14 M14ALCS(MOD. 0) stock (buttstock)"
        ],
        "ergonomics": 5.0,
        "gridsize": "1x1",
        "itemLink": "https://escapefromtarkov.gamepedia.com/M14ALCS(MOD._0)_pistol_grip_for_M14",
        "itemName": "M14ALCS(MOD. 0) pistol grip for M14",
        "recoil%": 0.0,
        "soldby": "Mechanic LL3",
        "type": "Pistol grip",
        "weight": 0.08
    },
    {
        "Compatibility": [
            "AKS-74 5.45x39 assault rifle",
            "AK-74 5.45x39 assault rifle",
            "Saiga 12ga ver. 10 12x76 assault rifle",
            "AK-103 7.62x39 assault rifle",
            "AKMS 7.62x39 assault rifle",
            "Saiga-9 9x19 Carbine",
            "AKMN 7.62x39 assault rifle",
            "AK-74N 5.45x39 assault rifle",
            "Vepr KM / VPO-136 7.62x39 carbine",
            "AK-74M 5.45x39 assault rifle",
            "AK-105 5.45x39 assault rifle",
            "Vepr AKM / VPO-209 366TKM carbine",
            "Submachinegun 19-01 Vityaz-SN 9x19",
            "AKM 7.62x39 assault rifle",
            "Kalashnikov AKS-74UB 5.45x39",
            "AKMSN 7.62x39 assault rifle",
            "AK-102 5.56x45 assault rifle",
            "Kalashnikov AKS-74U 5.45x39",
            "AK-101 5.56x45 assault rifle",
            "Kalashnikov AKS-74UN 5.45x39",
            "AK-104 7.62x39 assault rifle",
            "AKS-74N 5.45x39 assault rifle",
            "RPK-16 5.45x39 light machine gun"
        ],
        "ergonomics": 7.0,
        "gridsize": "1x1",
        "itemLink": "https://escapefromtarkov.gamepedia.com/PP-19-01_Izhmash_pistol_grip",
        "itemName": "PP-19-01 Izhmash pistol grip",
        "recoil%": 0.0,
        "soldby": "Prapor LL2",
        "type": "Pistol grip",
        "weight": 0.07
    },
    {
        "Compatibility": [
            "TOZ stock for TOZ-106"
        ],
        "ergonomics": 3.0,
        "gridsize": "1x1",
        "itemLink": "https://escapefromtarkov.gamepedia.com/TOZ_002_pistol_grip_for_TOZ-106",
        "itemName": "TOZ 002 pistol grip for TOZ-106",
        "recoil%": 0.0,
        "type": "Pistol grip",
        "weight": 0.07
    },
    {
        "Compatibility": [
            "Yarygin MP-443 Grach 9x19 pistol"
        ],
        "ergonomics": 5.0,
        "gridsize": "1x1",
        "itemLink": "https://escapefromtarkov.gamepedia.com/Polymer_Izhmekh_pistol_grip_for_MP-443",
        "itemName": "Polymer Izhmekh pistol grip for MP-443",
        "recoil%": 0.0,
        "soldby": "Prapor LL2",
        "type": "Pistol grip",
        "weight": 0.055
    },
    {
        "Compatibility": [
            "P226R 9x19 pistol"
        ],
        "ergonomics": 6.0,
        "gridsize": "1x1",
        "itemLink": "https://escapefromtarkov.gamepedia.com/Sig_Sauer_pistol_grip_for_P226",
        "itemName": "Sig Sauer pistol grip for P226",
        "recoil%": 0.0,
        "soldby": "Peacekeeper LL2 (FDE)",
        "type": "Pistol grip",
        "weight": 0.09
    },
    {
        "Compatibility": [
            "PB 9x18PM silenced pistol"
        ],
        "ergonomics": 5.0,
        "gridsize": "1x1",
        "itemLink": "https://escapefromtarkov.gamepedia.com/TSNIITOCHMASH_bakelite_PB_side_grips",
        "itemName": "TSNIITOCHMASH bakelite PB side grips",
        "recoil%": 0.0,
        "type": "Pistol grip",
        "weight": 0.102
    },
    {
        "Compatibility": [
            "TT pistol 7.62x25 TT Gold",
            "TT pistol 7.62x25 TT"
        ],
        "ergonomics": 5.0,
        "gridsize": "1x1",
        "itemLink": "https://escapefromtarkov.gamepedia.com/Fancy_TT_side_grips",
        "itemName": "Fancy TT side grips",
        "recoil%": 0.0,
        "type": "Pistol grip",
        "weight": 0.07
    },
    {
        "Compatibility": [
            "TT pistol 7.62x25 TT Gold",
            "TT pistol 7.62x25 TT"
        ],
        "ergonomics": 5.0,
        "gridsize": "1x1",
        "itemLink": "https://escapefromtarkov.gamepedia.com/Standard_TT_side_grips",
        "itemName": "Standard TT side grips",
        "recoil%": 0.0,
        "type": "Pistol grip",
        "weight": 0.07
    },
    {
        "Compatibility": [
            "SVDS 7.62x54 Sniper rifle",
            "AK-101 5.56x45 assault rifle",
            "AK-102 5.56x45 assault rifle",
            "AK-103 7.62x39 assault rifle",
            "AK-104 7.62x39 assault rifle",
            "AK-105 5.45x39 assault rifle",
            "AK-74 5.45x39 assault rifle",
            "AK-74M 5.45x39 assault rifle",
            "AK-74N 5.45x39 assault rifle",
            "AKM 7.62x39 assault rifle",
            "AKMN 7.62x39 assault rifle",
            "AKMS 7.62x39 assault rifle",
            "AKMSN 7.62x39 assault rifle",
            "AKS-74 5.45x39 assault rifle",
            "AKS-74N 5.45x39 assault rifle",
            "Kalashnikov AKS-74U 5.45x39",
            "Kalashnikov AKS-74UB 5.45x39",
            "Kalashnikov AKS-74UN 5.45x39",
            "RPK-16 5.45x39 light machine gun",
            "Saiga 12ga ver. 10 12x76 assault rifle",
            "Saiga-9 9x19 Carbine",
            "Submachinegun 19-01 Vityaz-SN 9x19",
            "Vepr AKM / VPO-209 366TKM carbine",
            "Vepr KM / VPO-136 7.62x39 carbine"
        ],
        "ergonomics": 5.0,
        "gridsize": "1x1",
        "itemLink": "https://escapefromtarkov.gamepedia.com/Izhmash_AK_bakelite_pistol_grip_(6P4_Sb.8V)",
        "itemName": "Izhmash AK bakelite pistol grip (6P4 Sb.8V)",
        "recoil%": 0.0,
        "soldby": "Prapor LL1",
        "type": "Pistol grip",
        "weight": 0.07
    },
    {
        "Compatibility": [
            "SVDS 7.62x54 Sniper rifle",
            "AK-101 5.56x45 assault rifle",
            "AK-102 5.56x45 assault rifle",
            "AK-103 7.62x39 assault rifle",
            "AK-104 7.62x39 assault rifle",
            "AK-105 5.45x39 assault rifle",
            "AK-74 5.45x39 assault rifle",
            "AK-74M 5.45x39 assault rifle",
            "AK-74N 5.45x39 assault rifle",
            "AKM 7.62x39 assault rifle",
            "AKMN 7.62x39 assault rifle",
            "AKMS 7.62x39 assault rifle",
            "AKMSN 7.62x39 assault rifle",
            "AKS-74 5.45x39 assault rifle",
            "AKS-74N 5.45x39 assault rifle",
            "Kalashnikov AKS-74U 5.45x39",
            "Kalashnikov AKS-74UB 5.45x39",
            "Kalashnikov AKS-74UN 5.45x39",
            "RPK-16 5.45x39 light machine gun",
            "Saiga 12ga ver. 10 12x76 assault rifle",
            "Saiga-9 9x19 Carbine",
            "Submachinegun 19-01 Vityaz-SN 9x19",
            "Vepr AKM / VPO-209 366TKM carbine",
            "Vepr KM / VPO-136 7.62x39 carbine"
        ],
        "ergonomics": 6.0,
        "gridsize": "1x1",
        "itemLink": "https://escapefromtarkov.gamepedia.com/Izhmash_AK_polymer_pistol_grip_(6P1_Sb.8)",
        "itemName": "Izhmash AK polymer pistol grip (6P1 Sb.8)",
        "recoil%": 0.0,
        "soldby": "Prapor LL1",
        "type": "Pistol grip",
        "weight": 0.065
    },
    {
        "Compatibility": [
            "SVDS 7.62x54 Sniper rifle",
            "AK-101 5.56x45 assault rifle",
            "AK-102 5.56x45 assault rifle",
            "AK-103 7.62x39 assault rifle",
            "AK-104 7.62x39 assault rifle",
            "AK-105 5.45x39 assault rifle",
            "AK-74 5.45x39 assault rifle",
            "AK-74M 5.45x39 assault rifle",
            "AK-74N 5.45x39 assault rifle",
            "AKM 7.62x39 assault rifle",
            "AKMN 7.62x39 assault rifle",
            "AKMS 7.62x39 assault rifle",
            "AKMSN 7.62x39 assault rifle",
            "AKS-74 5.45x39 assault rifle",
            "AKS-74N 5.45x39 assault rifle",
            "Kalashnikov AKS-74U 5.45x39",
            "Kalashnikov AKS-74UB 5.45x39",
            "Kalashnikov AKS-74UN 5.45x39",
            "RPK-16 5.45x39 light machine gun",
            "Saiga 12ga ver. 10 12x76 assault rifle",
            "Saiga-9 9x19 Carbine",
            "Submachinegun 19-01 Vityaz-SN 9x19",
            "Vepr AKM / VPO-209 366TKM carbine",
            "Vepr KM / VPO-136 7.62x39 carbine"
        ],
        "ergonomics": 5.0,
        "gridsize": "1x1",
        "itemLink": "https://escapefromtarkov.gamepedia.com/Izhmash_AKM_bakelite_pistol_grip",
        "itemName": "Izhmash AKM bakelite pistol grip",
        "recoil%": 0.0,
        "type": "Pistol grip",
        "weight": 0.07
    },
    {
        "Compatibility": [
            "SVDS 7.62x54 Sniper rifle",
            "AK-101 5.56x45 assault rifle",
            "AK-102 5.56x45 assault rifle",
            "AK-103 7.62x39 assault rifle",
            "AK-104 7.62x39 assault rifle",
            "AK-105 5.45x39 assault rifle",
            "AK-74 5.45x39 assault rifle",
            "AK-74M 5.45x39 assault rifle",
            "AK-74N 5.45x39 assault rifle",
            "AKM 7.62x39 assault rifle",
            "AKMN 7.62x39 assault rifle",
            "AKMS 7.62x39 assault rifle",
            "AKMSN 7.62x39 assault rifle",
            "AKS-74 5.45x39 assault rifle",
            "AKS-74N 5.45x39 assault rifle",
            "Kalashnikov AKS-74U 5.45x39",
            "Kalashnikov AKS-74UB 5.45x39",
            "Kalashnikov AKS-74UN 5.45x39",
            "RPK-16 5.45x39 light machine gun",
            "Saiga 12ga ver. 10 12x76 assault rifle",
            "Saiga-9 9x19 Carbine",
            "Submachinegun 19-01 Vityaz-SN 9x19",
            "Vepr AKM / VPO-209 366TKM carbine",
            "Vepr KM / VPO-136 7.62x39 carbine"
        ],
        "ergonomics": 5.0,
        "gridsize": "1x1",
        "itemLink": "https://escapefromtarkov.gamepedia.com/Wooden_Izhmash_AKM_pistol_grip_for_AK",
        "itemName": "Wooden Izhmash AKM pistol grip for AK",
        "recoil%": 0.0,
        "type": "Pistol grip",
        "weight": 0.07
    },
    {
        "Compatibility": [
            "SVDS 7.62x54 Sniper rifle",
            "AK-101 5.56x45 assault rifle",
            "AK-102 5.56x45 assault rifle",
            "AK-103 7.62x39 assault rifle",
            "AK-104 7.62x39 assault rifle",
            "AK-105 5.45x39 assault rifle",
            "AK-74 5.45x39 assault rifle",
            "AK-74M 5.45x39 assault rifle",
            "AK-74N 5.45x39 assault rifle",
            "AKM 7.62x39 assault rifle",
            "AKMN 7.62x39 assault rifle",
            "AKMS 7.62x39 assault rifle",
            "AKMSN 7.62x39 assault rifle",
            "AKS-74 5.45x39 assault rifle",
            "AKS-74N 5.45x39 assault rifle",
            "Kalashnikov AKS-74U 5.45x39",
            "Kalashnikov AKS-74UB 5.45x39",
            "Kalashnikov AKS-74UN 5.45x39",
            "RPK-16 5.45x39 light machine gun",
            "Saiga 12ga ver. 10 12x76 assault rifle",
            "Saiga-9 9x19 Carbine",
            "Submachinegun 19-01 Vityaz-SN 9x19",
            "Vepr AKM / VPO-209 366TKM carbine",
            "Vepr KM / VPO-136 7.62x39 carbine"
        ],
        "ergonomics": 5.0,
        "gridsize": "1x1",
        "itemLink": "https://escapefromtarkov.gamepedia.com/Izhmash_AK-74_Textolite_pistol_grip_(6P4_Sb.9)",
        "itemName": "Izhmash AK-74 Textolite pistol grip (6P4 Sb.9)",
        "recoil%": 0.0,
        "soldby": "Prapor LL1",
        "type": "Pistol grip",
        "weight": 0.07
    },
    {
        "Compatibility": [
            "SVDS 7.62x54 Sniper rifle",
            "AK-101 5.56x45 assault rifle",
            "AK-102 5.56x45 assault rifle",
            "AK-103 7.62x39 assault rifle",
            "AK-104 7.62x39 assault rifle",
            "AK-105 5.45x39 assault rifle",
            "AK-74 5.45x39 assault rifle",
            "AK-74M 5.45x39 assault rifle",
            "AK-74N 5.45x39 assault rifle",
            "AKM 7.62x39 assault rifle",
            "AKMN 7.62x39 assault rifle",
            "AKMS 7.62x39 assault rifle",
            "AKMSN 7.62x39 assault rifle",
            "AKS-74 5.45x39 assault rifle",
            "AKS-74N 5.45x39 assault rifle",
            "Kalashnikov AKS-74U 5.45x39",
            "Kalashnikov AKS-74UB 5.45x39",
            "Kalashnikov AKS-74UN 5.45x39",
            "RPK-16 5.45x39 light machine gun",
            "Saiga 12ga ver. 10 12x76 assault rifle",
            "Saiga-9 9x19 Carbine",
            "Submachinegun 19-01 Vityaz-SN 9x19",
            "Vepr AKM / VPO-209 366TKM carbine",
            "Vepr KM / VPO-136 7.62x39 carbine"
        ],
        "ergonomics": 5.0,
        "gridsize": "1x1",
        "itemLink": "https://escapefromtarkov.gamepedia.com/Molot_AK_bakelite_pistol_grip",
        "itemName": "Molot AK bakelite pistol grip",
        "recoil%": 0.0,
        "soldby": "Skier LL1",
        "type": "Pistol grip",
        "weight": 0.07
    },
    {
        "Compatibility": [
            "SVDS 7.62x54 Sniper rifle",
            "AKS-74 5.45x39 assault rifle",
            "AK-74 5.45x39 assault rifle",
            "Saiga 12ga ver. 10 12x76 assault rifle",
            "AK-103 7.62x39 assault rifle",
            "AKMS 7.62x39 assault rifle",
            "Saiga-9 9x19 Carbine",
            "AKMN 7.62x39 assault rifle",
            "AK-74N 5.45x39 assault rifle",
            "Vepr KM / VPO-136 7.62x39 carbine",
            "AK-74M 5.45x39 assault rifle",
            "AK-105 5.45x39 assault rifle",
            "Vepr AKM / VPO-209 366TKM carbine",
            "Submachinegun 19-01 Vityaz-SN 9x19",
            "AKM 7.62x39 assault rifle",
            "Kalashnikov AKS-74UB 5.45x39",
            "AKMSN 7.62x39 assault rifle",
            "AK-102 5.56x45 assault rifle",
            "Kalashnikov AKS-74U 5.45x39",
            "AK-101 5.56x45 assault rifle",
            "Kalashnikov AKS-74UN 5.45x39",
            "AK-104 7.62x39 assault rifle",
            "AKS-74N 5.45x39 assault rifle",
            "RPK-16 5.45x39 light machine gun"
        ],
        "ergonomics": 10.0,
        "gridsize": "1x1",
        "itemLink": "https://escapefromtarkov.gamepedia.com/TAPCO_SAW-Style_pistol_grip_for_AK",
        "itemName": "TAPCO SAW-Style pistol grip for AK",
        "recoil%": 0.0,
        "soldby": "Peacekeeper LL2",
        "type": "Pistol grip",
        "weight": 0.13
    },
    {
        "Compatibility": [
            "SVDS 7.62x54 Sniper rifle",
            "AK-101 5.56x45 assault rifle",
            "AK-102 5.56x45 assault rifle",
            "AK-103 7.62x39 assault rifle",
            "AK-104 7.62x39 assault rifle",
            "AK-105 5.45x39 assault rifle",
            "AK-74 5.45x39 assault rifle",
            "AK-74M 5.45x39 assault rifle",
            "AK-74N 5.45x39 assault rifle",
            "AKM 7.62x39 assault rifle",
            "AKMN 7.62x39 assault rifle",
            "AKMS 7.62x39 assault rifle",
            "AKMSN 7.62x39 assault rifle",
            "AKS-74 5.45x39 assault rifle",
            "AKS-74N 5.45x39 assault rifle",
            "Kalashnikov AKS-74U 5.45x39",
            "Kalashnikov AKS-74UB 5.45x39",
            "Kalashnikov AKS-74UN 5.45x39",
            "RPK-16 5.45x39 light machine gun",
            "Saiga 12ga ver. 10 12x76 assault rifle",
            "Saiga-9 9x19 Carbine",
            "Submachinegun 19-01 Vityaz-SN 9x19",
            "Vepr AKM / VPO-209 366TKM carbine",
            "Vepr KM / VPO-136 7.62x39 carbine"
        ],
        "ergonomics": 13.0,
        "gridsize": "1x1",
        "itemLink": "https://escapefromtarkov.gamepedia.com/Zenit_RK-3_AK_pistol_grip",
        "itemName": "Zenit RK-3 AK pistol grip",
        "recoil%": 0.0,
        "soldby": "Skier LL2",
        "type": "Pistol grip",
        "weight": 0.225
    },
    {
        "Compatibility": [
            "Silenced Stechkin Automatic Pistol 9x18PM",
            "Stechkin Automatic Pistol 9x18PM"
        ],
        "ergonomics": 5.0,
        "gridsize": "1x1",
        "itemLink": "https://escapefromtarkov.gamepedia.com/APS_bakelite_side-pieces",
        "itemName": "APS bakelite side-pieces",
        "recoil%": 0.0,
        "type": "Pistol grip",
        "weight": 0.102
    },
    {
        "Compatibility": [
            "HK 416A5 5.56x45 Assault Rifle",
            "ADAR 2-15 .223 Carbine",
            "LEO stock adapter for M870",
            "Troy S.A.S.S. Chassis stock for M14",
            "Colt M4A1 5.56x45 Assault Rifle",
            "DVL-10 Saboteur sniper rifle",
            "Remington R11 RSASS 7.62x51",
            "SIG MPX 9x19 Submachine gun"
        ],
        "ergonomics": 5.0,
        "gridsize": "1x1",
        "itemLink": "https://escapefromtarkov.gamepedia.com/Colt_A2_AR-15_pistol_grip",
        "itemName": "Colt A2 AR-15 pistol grip",
        "recoil%": 0.0,
        "soldby": "Peacekeeper LL1",
        "type": "Pistol grip",
        "weight": 0.08
    },
    {
        "Compatibility": [
            "HK 416A5 5.56x45 Assault Rifle",
            "ADAR 2-15 .223 Carbine",
            "LEO stock adapter for M870",
            "Troy S.A.S.S. Chassis stock for M14",
            "Colt M4A1 5.56x45 Assault Rifle",
            "DVL-10 Saboteur sniper rifle",
            "Remington R11 RSASS 7.62x51",
            "SIG MPX 9x19 Submachine gun"
        ],
        "ergonomics": 5.0,
        "gridsize": "1x1",
        "itemLink": "https://escapefromtarkov.gamepedia.com/DI_ECS_FDE_pistol_grip_for_AR-15_based_systems",
        "itemName": "DI ECS FDE pistol grip for AR-15 based systems",
        "recoil%": 0.0,
        "soldby": "Skier LL2",
        "type": "Pistol grip",
        "weight": 0.08
    },
    {
        "Compatibility": [
            "Colt M4A1 5.56x45 Assault Rifle",
            "ADAR 2-15 .223 Carbine"
        ],
        "ergonomics": 18.0,
        "gridsize": "1x1",
        "itemLink": "https://escapefromtarkov.gamepedia.com/Hera_Arms_CQR_pistol_grip-stock",
        "itemName": "Hera Arms CQR pistol grip-stock",
        "recoil%": -39.0,
        "soldby": "Mechanic LL4",
        "type": "Pistol grip",
        "weight": 0.499
    },
    {
        "Compatibility": [
            "HK 416A5 5.56x45 Assault Rifle",
            "ADAR 2-15 .223 Carbine",
            "LEO stock adapter for M870",
            "Troy S.A.S.S. Chassis stock for M14",
            "Colt M4A1 5.56x45 Assault Rifle",
            "DVL-10 Saboteur sniper rifle",
            "Remington R11 RSASS 7.62x51",
            "SIG MPX 9x19 Submachine gun"
        ],
        "ergonomics": 9.0,
        "gridsize": "1x1",
        "itemLink": "https://escapefromtarkov.gamepedia.com/Hogue_OverMolded_Rubber_Grip",
        "itemName": "Hogue OverMolded Rubber Grip",
        "recoil%": 0.0,
        "soldby": "Peacekeeper LL3",
        "type": "Pistol grip",
        "weight": 0.08
    },
    {
        "Compatibility": [
            "HK 416A5 5.56x45 Assault Rifle",
            "ADAR 2-15 .223 Carbine",
            "LEO stock adapter for M870",
            "Troy S.A.S.S. Chassis stock for M14",
            "Colt M4A1 5.56x45 Assault Rifle",
            "DVL-10 Saboteur sniper rifle",
            "Remington R11 RSASS 7.62x51",
            "SIG MPX 9x19 Submachine gun"
        ],
        "ergonomics": 8.0,
        "gridsize": "1x1",
        "itemLink": "https://escapefromtarkov.gamepedia.com/MIAD_Pistol_grip_for_AR-15_based_systems",
        "itemName": "MIAD Pistol grip for AR-15 based systems",
        "recoil%": 0.0,
        "soldby": "Peacekeeper LL3",
        "type": "Pistol grip",
        "weight": 0.05
    },
    {
        "Compatibility": [
            "HK 416A5 5.56x45 Assault Rifle",
            "ADAR 2-15 .223 Carbine",
            "SIG MPX 9x19 Submachine gun",
            "Colt M4A1 5.56x45 Assault Rifle",
            "Remington R11 RSASS 7.62x51"
        ],
        "ergonomics": 10.0,
        "gridsize": "1x1",
        "itemLink": "https://escapefromtarkov.gamepedia.com/Magpul_MOE_AR-15_pistol_grip",
        "itemName": "Magpul MOE AR-15 pistol grip",
        "recoil%": 0.0,
        "type": "Pistol grip",
        "weight": 0.05
    },
    {
        "Compatibility": [
            "HK 416A5 5.56x45 Assault Rifle",
            "ADAR 2-15 .223 Carbine",
            "Colt M4A1 5.56x45 Assault Rifle",
            "Remington R11 RSASS 7.62x51",
            "SIG MPX 9x19 Submachine gun"
        ],
        "ergonomics": 15.0,
        "gridsize": "1x1",
        "itemLink": "https://escapefromtarkov.gamepedia.com/Naroh_Arms_GRAL-S_Pistol_grip_for_AR-15-compatible_weapons",
        "itemName": "Naroh Arms GRAL-S Pistol grip for AR-15-compatible weapons",
        "recoil%": 0.0,
        "soldby": "Peacekeeper LL4",
        "type": "Pistol grip",
        "weight": 0.092
    },
    {
        "Compatibility": [
            "HK 416A5 5.56x45 Assault Rifle",
            "ADAR 2-15 .223 Carbine",
            "Colt M4A1 5.56x45 Assault Rifle",
            "Remington R11 RSASS 7.62x51",
            "SIG MPX 9x19 Submachine gun"
        ],
        "ergonomics": 11.0,
        "gridsize": "1x1",
        "itemLink": "https://escapefromtarkov.gamepedia.com/Stark_AR_Rifle_Grip_for_AR-15-compatible_weapons",
        "itemName": "Stark AR Rifle Grip for AR-15-compatible weapons",
        "recoil%": 0.0,
        "soldby": "Peacekeeper LL4",
        "type": "Pistol grip",
        "weight": 0.09
    },
    {
        "Compatibility": [
            "SIG MPX 9x19 Submachine gun"
        ],
        "ergonomics": 5.0,
        "gridsize": "1x1",
        "itemLink": "https://escapefromtarkov.gamepedia.com/Pistol_grip_SIG_MPX",
        "itemName": "Pistol grip SIG MPX",
        "recoil%": 0.0,
        "type": "Pistol grip",
        "weight": 0.07
    },
    {
        "Compatibility": [
            "PP-9 Klin 9x18PMM SMG",
            "PP-91 Kedr 9x18PM SMG",
            "PP-91-01 Kedr-B 9x18PM SMG"
        ],
        "ergonomics": 5.0,
        "gridsize": "1x1",
        "itemLink": "https://escapefromtarkov.gamepedia.com/ZMZ_Polymer_pistol_grip_for_PP-91",
        "itemName": "ZMZ Polymer pistol grip for PP-91",
        "recoil%": 0.0,
        "type": "Pistol grip",
        "weight": 0.071
    },
    {
        "Compatibility": [
            "AS VAL"
        ],
        "ergonomics": 5.0,
        "gridsize": "1x1",
        "itemLink": "https://escapefromtarkov.gamepedia.com/AS_VAL_Pistol_grip",
        "itemName": "AS VAL Pistol grip",
        "recoil%": 0.0,
        "soldby": "Prapor LL3",
        "type": "Pistol grip",
        "weight": 0.146
    },
    {
        "Compatibility": [
            "GLOCK 18C 9x19 pistol",
            "GLOCK 17 9x19 pistol"
        ],
        "ergonomics": 7.0,
        "gridsize": "1x1",
        "itemLink": "https://escapefromtarkov.gamepedia.com/Pachmayr_tactical_rubber_grip",
        "itemName": "Pachmayr tactical rubber grip",
        "recoil%": 0.0,
        "soldby": "Mechanic LL2",
        "type": "Pistol grip",
        "weight": 0.08
    },
    {
        "Compatibility": [
            "HK 416A5 5.56x45 Assault Rifle",
            "ADAR 2-15 .223 Carbine",
            "SIG MPX 9x19 Submachine gun",
            "LEO stock adapter for M870",
            "Troy S.A.S.S. Chassis stock for M14",
            "Colt M4A1 5.56x45 Assault Rifle",
            "DVL-10 Saboteur sniper rifle",
            "Remington R11 RSASS 7.62x51"
        ],
        "ergonomics": 6.0,
        "gridsize": "1x1",
        "itemLink": "https://escapefromtarkov.gamepedia.com/Skeletonized_AR-15_pistol_grip",
        "itemName": "Skeletonized AR-15 pistol grip",
        "recoil%": 0.0,
        "soldby": "Mechanic LL4 after completing his task Gunsmith - Part 13",
        "type": "Pistol grip",
        "weight": 0.038
    },
    {
        "Compatibility": [
            "AS VAL"
        ],
        "ergonomics": 5.0,
        "gridsize": "2x1",
        "itemLink": "https://escapefromtarkov.gamepedia.com/AS_VAL_Pistol_grip-buffer_tube",
        "itemName": "AS VAL Pistol grip-buffer tube",
        "recoil%": 0.0,
        "soldby": "Mechanic LL2",
        "type": "Pistol grip",
        "weight": 0.065
    },
    {
        "Compatibility": [
            "Tapco INTRAFUSE Stock for SKS"
        ],
        "ergonomics": 10.0,
        "gridsize": "1x1",
        "itemLink": "https://escapefromtarkov.gamepedia.com/TAPCO_SAW-Style_pistol_grip_for_SKS_INTRAFUSE_Kit",
        "itemName": "TAPCO SAW-Style pistol grip for SKS INTRAFUSE Kit",
        "recoil%": 0.0,
        "soldby": "Mechanic LL2",
        "type": "Pistol grip",
        "weight": 0.09
    }
]