[
    {
        "acceptedammunition": "\n12x70 Buckshot\n12x70 RIP\n12x70 Slug",
        "caliber": "12x70mm",
        "defaultammo": "12x70 Buckshot",
        "defaultmag": "4-shell M870 12ga magazine cap",
        "effectivedistance": "70 m",
        "ergonomics": 48.0,
        "examineexperience": 4.0,
        "firingmodes": "Single",
        "gridsize": "5x1",
        "horizontalRecoil": 650.0,
        "itemLink": "https://escapefromtarkov.gamepedia.com/M870",
        "itemName": "Remington Model 870 12ga shotgun",
        "lootexperience": 20.0,
        "muzzlevelocity": 337.0,
        "rateoffire(rpm)": "30",
        "sightingrange": "100",
        "slot": "Primary",
        "soldby": "Skier LL1",
        "type": "Shotgun",
        "verticalRecoil": 520.0,
        "weight": 3.14
    },
    {
        "acceptedammunition": "\n12x70 Buckshot\n12x70 RIP\n12x70 Slug",
        "caliber": "12x70mm",
        "defaultammo": "12x70 Buckshot",
        "defaultmag": "6-shell MP-133x6 12ga magazine",
        "effectivedistance": "70 m",
        "ergonomics": 49.0,
        "firingmodes": "Single",
        "gridsize": "5x1",
        "horizontalRecoil": 650.0,
        "itemLink": "https://escapefromtarkov.gamepedia.com/MP-133",
        "itemName": "MP-133 12ga shotgun",
        "lootexperience": 20.0,
        "muzzlevelocity": 337.0,
        "rateoffire(rpm)": "30",
        "sightingrange": "100",
        "slot": "Primary",
        "soldby": "Skier LL1",
        "type": "Shotgun",
        "verticalRecoil": 520.0,
        "weight": 3.54
    },
    {
        "acceptedammunition": "\n12x70 Buckshot\n12x70 RIP\n12x70 Slug",
        "caliber": "12x70mm",
        "defaultammo": "12x70 Buckshot",
        "defaultmag": "MP-153 foreend cap",
        "effectivedistance": "70 m",
        "ergonomics": 40.0,
        "examineexperience": 6.0,
        "firingmodes": "Single",
        "gridsize": "7x1",
        "horizontalRecoil": 585.0,
        "itemLink": "https://escapefromtarkov.gamepedia.com/MP-153",
        "itemName": "MP-153 12ga semi-automatic shotgun",
        "lootexperience": 30.0,
        "muzzlevelocity": 377.0,
        "rateoffire(rpm)": "40",
        "sightingrange": "100",
        "slot": "Primary",
        "soldby": "Skier LL2",
        "type": "Shotgun",
        "verticalRecoil": 455.0,
        "weight": 3.62
    },
    {
        "acceptedammunition": "\n12x70 Buckshot\n12x70 RIP\n12x70 Slug",
        "caliber": "12x70mm",
        "defaultammo": "12x70 Buckshot",
        "defaultmag": "Sb.5 5-round 12x76 magazine for SOK-12 and compatible weapons",
        "effectivedistance": "70 m",
        "ergonomics": 55.0,
        "firingmodes": "Single",
        "gridsize": "5x2",
        "horizontalRecoil": 650.0,
        "itemLink": "https://escapefromtarkov.gamepedia.com/Saiga-12",
        "itemName": "Saiga 12ga ver. 10 12x76 assault rifle",
        "lootexperience": 20.0,
        "muzzlevelocity": 328.0,
        "rateoffire(rpm)": "40",
        "sightingrange": "100",
        "slot": "Primary",
        "soldby": "Prapor LL2 Skier LL2",
        "type": "Shotgun",
        "verticalRecoil": 390.0,
        "weight": 3.6
    },
    {
        "acceptedammunition": "\n20x70 Buckshot",
        "caliber": "20x70mm",
        "defaultammo": "20x70 Buckshot",
        "defaultmag": "2-shot MC 20-01 Sb.3 20ga magazine for TOZ-106",
        "effectivedistance": "70 m",
        "ergonomics": 68.0,
        "examineexperience": 10.0,
        "firingmodes": "Single",
        "gridsize": "3x1",
        "horizontalRecoil": 650.0,
        "itemLink": "https://escapefromtarkov.gamepedia.com/TOZ-106",
        "itemName": "TOZ-106 bolt-action shotgun",
        "lootexperience": 20.0,
        "muzzlevelocity": 325.0,
        "rateoffire(rpm)": "30",
        "sightingrange": "100",
        "slot": "Primary",
        "soldby": "Skier LL1",
        "type": "Shotgun",
        "verticalRecoil": 780.0,
        "weight": 2.715
    }
]